{
  "cookies": [
    {
      "name": "session-username",
      "value": "standard_user",
      "domain": "www.saucedemo.com",
      "path": "/",
      "expires": 1774682519,
      "httpOnly": false,
      "secure": false,
      "sameSite": "Lax"
    }
  ],
  "origins": [
    {
      "origin": "https://www.saucedemo.com",
      "localStorage": [
        {
          "name": "backtrace-guid",
          "value": "8a70a87d-a81a-4620-a01e-316f309a9440"
        },
        {
          "name": "backtrace-last-active",
          "value": "1774681918998"
        }
      ]
    }
  ]
}